TT_probability_package/__init__.py
TT_probability_package/analyser_module.py
TT_probability_package/card_deck_module.py
TT_probability_package/coin_module.py
TT_probability_package/dice_module.py
TT_probability_package/game_simulation_module.py
tt_probability_package-0.1.1.dist-info/licenses/LICENSE
tt_probability_package-0.1.1.dist-info/METADATA
tt_probability_package-0.1.1.dist-info/WHEEL
tt_probability_package-0.1.1.dist-info/top_level.txt
tt_probability_package-0.1.1.dist-info/RECORD
